tf_latino/__init__.py
tf_latino/latino/__init__.py
tf_latino/latino/interaction_views.py
tf_latino/latino/library.py
tf_latino/latino/library_gen.py
tf_latino/latino/library_manual.py
tf_latino/latino/urls.py
tf_latino/latino/views.py
tf_latino/latino/visualization_views.py
tf_latino/latino/management/__init__.py
tf_latino/latino/management/commands/__init__.py
tf_latino/latino/management/commands/reverse_csharp_widget_def.py
tf_latino/latino/package_data/categories/0378e3a8-b71e-47b5-96b0-84dca2680f4d.json
tf_latino/latino/package_data/categories/05c26564-86b5-4a73-aae9-f4dc14bc75d7.json
tf_latino/latino/package_data/categories/08c17c78-3f4d-4006-8b3f-1ee34bca5ccd.json
tf_latino/latino/package_data/categories/1b800757-2c72-4663-b3e4-2f2b61f609ff.json
tf_latino/latino/package_data/categories/1eed1020-c423-4831-80ce-50f65ae276e1.json
tf_latino/latino/package_data/categories/2e5cfc0a-c916-45b3-b53f-c3234a408bbd.json
tf_latino/latino/package_data/categories/46050a99-188d-40e1-90e5-0c1912059fa7.json
tf_latino/latino/package_data/categories/48fb3ce2-11ef-4afc-ab1e-aec6f1d6d055.json
tf_latino/latino/package_data/categories/49d5fda2-23d4-444a-a6df-3c5714d2fdfd.json
tf_latino/latino/package_data/categories/4b74b12d-4767-45b1-9bb3-8872234b01fe.json
tf_latino/latino/package_data/categories/57cfe571-165d-4575-90d9-28daf794e773.json
tf_latino/latino/package_data/categories/5a2a3054-1e34-4e51-851e-85baaee020d4.json
tf_latino/latino/package_data/categories/5a4286c8-d182-45a5-896b-cc3c6ed84f22.json
tf_latino/latino/package_data/categories/5f0ee744-65c5-4878-81c8-dab76f6e5976.json
tf_latino/latino/package_data/categories/6091637f-b3cd-4559-b525-18357b02dbc2.json
tf_latino/latino/package_data/categories/64780432-b114-4589-a24c-2331aed23502.json
tf_latino/latino/package_data/categories/70b1a1cf-49e8-479b-a8d8-32cc2fbfa47b.json
tf_latino/latino/package_data/categories/74457dca-9fba-4d66-98dd-633df385a22b.json
tf_latino-0.0.5.dist-info/DESCRIPTION.rst
tf_latino-0.0.5.dist-info/METADATA
tf_latino-0.0.5.dist-info/RECORD
tf_latino-0.0.5.dist-info/WHEEL
tf_latino-0.0.5.dist-info/metadata.json
tf_latino-0.0.5.dist-info/top_level.txt
